Metadata-Version: 2.4
Name: sphinxcontrib-plantuml
Version: 0.31
Summary: Sphinx "plantuml" extension
Home-page: https://github.com/sphinx-contrib/plantuml/
Download-URL: https://pypi.python.org/pypi/sphinxcontrib-plantuml
Author: Yuya Nishihara
Author-email: yuya@tcha.org
License: BSD
Platform: any
Classifier: Development Status :: 4 - Beta
Classifier: Environment :: Console
Classifier: Environment :: Web Environment
Classifier: Framework :: Sphinx :: Extension
Classifier: Intended Audience :: Developers
Classifier: License :: OSI Approved :: BSD License
Classifier: Operating System :: OS Independent
Classifier: Programming Language :: Python
Classifier: Topic :: Documentation
Classifier: Topic :: Utilities
License-File: LICENSE
Requires-Dist: Sphinx>=1.6
Provides-Extra: test
Requires-Dist: Pillow; extra == "test"
Requires-Dist: flake8; extra == "test"
Requires-Dist: pytest; extra == "test"
Dynamic: author
Dynamic: author-email
Dynamic: classifier
Dynamic: description
Dynamic: download-url
Dynamic: home-page
Dynamic: license
Dynamic: license-file
Dynamic: platform
Dynamic: summary
